perfsprocket/__init__.py
perfsprocket/_class_file.py
perfsprocket/_class_file_base.py
perfsprocket/_class_file_sequence.py
perfsprocket/_file_abc.py
perfsprocket/_file_name.py
perfsprocket/_helpers_private.py
perfsprocket/_version.py
perfsprocket-0.2.1.dist-info/LICENSE
perfsprocket-0.2.1.dist-info/METADATA
perfsprocket-0.2.1.dist-info/WHEEL
perfsprocket-0.2.1.dist-info/top_level.txt
perfsprocket-0.2.1.dist-info/RECORD
